pi_printer.py
test_numpy.py
pi_printer_test-1.0.0.dist-info/LICENSE
pi_printer_test-1.0.0.dist-info/METADATA
pi_printer_test-1.0.0.dist-info/WHEEL
pi_printer_test-1.0.0.dist-info/entry_points.txt
pi_printer_test-1.0.0.dist-info/top_level.txt
pi_printer_test-1.0.0.dist-info/RECORD
